embed_all/__init__.py
embed_all/index.py
embed_all-0.0.5.dist-info/METADATA
embed_all-0.0.5.dist-info/WHEEL
embed_all-0.0.5.dist-info/licenses/LICENSE
embed_all-0.0.5.dist-info/RECORD
