Metadata-Version: 2.3
Name: embed_all
Version: 0.0.5
Summary: Add your description here
Author-email: Arnab Bhattacharya <53032587+Arnab28122000@users.noreply.github.com>
License-File: LICENSE
Requires-Python: >=3.8
Requires-Dist: openpyxl>=3.1.5
Requires-Dist: pandas>=2.2.2
